{
  "packages": [
    {
      "name": "soya",
      "websiteURL": "https://oratek.com",
      "email": "hello@oratek.com",
      "maintainer": "Oratek",
      "platforms":
      [
        {
          "architecture": "avr",
          "name": "Oratek Soya Boards",
          "category": "Soya",
          "version": "1.0.0",
          "archiveFileName": "soya-main.zip",
          "size": "259347",
          "checksum": "SHA-256:5f4f61715a559567f2db2e4a6fd13a05058a8f542a165d2a3be884890f135955",
          "url": "https://github.com/Sestre-oratek/soya/archive/main.zip",
          "boards": [
            {
              "name": "Soya L"
            },
            {
              "name": "Soya B"
            },
            {
              "name": "Soya G"
            }
          ],
          "toolsDependencies":
          [
            {
              "name": "avr-gcc",
              "packager": "arduino",
              "version": "4.8.1-arduino5"
            },
            {
              "name": "avrdude",
              "packager": "arduino",
              "version": "6.0.1-arduino5"
            }
          ]
        }
      ]
    }
  ]
}